httping.py
setup.py
httping.egg-info/PKG-INFO
httping.egg-info/SOURCES.txt
httping.egg-info/dependency_links.txt
httping.egg-info/top_level.txt